jiggle_version/__about__.py
jiggle_version/__init__.py
jiggle_version/__main__.py
jiggle_version/auto.py
jiggle_version/bump.py
jiggle_version/config.py
jiggle_version/discover.py
jiggle_version/git.py
jiggle_version/gitignore.py
jiggle_version/py.typed
jiggle_version/pypi.py
jiggle_version/schemes.py
jiggle_version/update.py
jiggle_version/parsers/__init__.py
jiggle_version/parsers/ast_parser.py
jiggle_version/parsers/config_parser.py
jiggle_version/utils/__init__.py
jiggle_version/utils/cli_suggestions.py
jiggle_version/utils/logging_config.py
jiggle_version-2.1.0.dist-info/METADATA
jiggle_version-2.1.0.dist-info/WHEEL
jiggle_version-2.1.0.dist-info/entry_points.txt
jiggle_version-2.1.0.dist-info/licenses/LICENSE
jiggle_version-2.1.0.dist-info/RECORD
