Metadata-Version: 2.4
Name: jiggle_version
Version: 2.1.0
Summary: Increment version number found in source code without regex
Author-email: Matthew Martin <matthewdeanmartin@gmail.com>
License-Expression: MIT
License-File: LICENSE
Keywords: version,version-numbers
Classifier: Development Status :: 3 - Alpha
Classifier: Programming Language :: Python
Classifier: Programming Language :: Python :: 3
Classifier: Programming Language :: Python :: 3.8
Classifier: Programming Language :: Python :: 3.9
Classifier: Programming Language :: Python :: 3.10
Classifier: Programming Language :: Python :: 3.11
Classifier: Programming Language :: Python :: 3.12
Classifier: Programming Language :: Python :: 3.13
Classifier: Programming Language :: Python :: 3.14
Classifier: Programming Language :: Python :: 3.15
Requires-Python: >=3.8
Requires-Dist: packaging>=25.0
Requires-Dist: pathspec>=0.12
Requires-Dist: requests>=2.32.4
Requires-Dist: rich-argparse>=1.7.1
Requires-Dist: tomli; python_version < '3.11'
Requires-Dist: tomlkit>=0.13.3
